<?xml version="1.0" encoding="UTF-8"?>
<con:soapui-project id="29523353-1cfc-45c5-b8f7-0da6f7b37633" activeEnvironment="Default" name="REST Project 1" resourceRoot="" soapui-version="5.6.0" xmlns:con="http://eviware.com/soapui/config"><con:settings/><con:interface xsi:type="con:RestService" id="bdf1d5e0-a78d-4ad6-a01a-13e9c0ef3093" wadlVersion="http://wadl.dev.java.net/2009/02" name="http://development.mawashi.tools:8080" type="rest" xmlns:xsi="http://www.w3.org/2001/XMLSchema-instance"><con:settings/><con:definitionCache type="TEXT" rootPart=""/><con:endpoints><con:endpoint>http://development.mawashi.tools:8080</con:endpoint></con:endpoints><con:resource name="v1.0" path="/api/rest/v1.0" id="8a19f57b-1a0d-467b-986d-acd65688d876"><con:settings/><con:parameters><con:parameter><con:name>Authorization</con:name><con:style>HEADER</con:style></con:parameter><con:parameter><con:name>tokenType</con:name><con:value/><con:style>PLAIN</con:style><con:default/><con:description xsi:nil="true"/></con:parameter><con:parameter><con:name>token</con:name><con:value/><con:style>PLAIN</con:style><con:default/><con:description xsi:nil="true"/></con:parameter></con:parameters><con:resource name="auth" path="auth" id="1940376a-34cd-47de-bb10-20ba4602aab0"><con:settings/><con:parameters/><con:resource name="signup" path="signup" id="6eef65b1-0400-4571-9f15-b8a0a9a0e17c"><con:settings/><con:parameters/><con:method name="Method 1" id="0eafa999-b0a6-4c32-b0fb-60dc8c164faf" method="POST"><con:settings/><con:parameters/><con:representation type="FAULT"><con:mediaType>application/json</con:mediaType><con:status>400</con:status><con:params/><con:element xmlns:sig="http://development.mawashi.tools/api/rest/v1.0/auth/signup">sig:Fault</con:element></con:representation><con:representation type="REQUEST"><con:mediaType>application/json</con:mediaType><con:params/></con:representation><con:representation type="RESPONSE"><con:mediaType>application/json</con:mediaType><con:status>201</con:status><con:params/><con:element xmlns:sig="http://development.mawashi.tools/api/rest/v1.0/auth/signup">sig:Response</con:element></con:representation><con:request name="Request 1" id="eed712fe-9537-417d-ae64-84d705681521" mediaType="application/json" postQueryString="false"><con:settings><con:setting id="com.eviware.soapui.impl.wsdl.WsdlRequest@request-headers">&lt;xml-fragment/></con:setting></con:settings><con:endpoint>http://development.mawashi.tools:8080</con:endpoint><con:request>{
	"account":"alinka",
	"password":"alinana25",
	"username":"alinka25@aaa.aaa"
	
	}</con:request><con:originalUri>http://development.mawashi.tools/api/rest/v1.0/auth/signup</con:originalUri><con:credentials><con:authType>No Authorization</con:authType></con:credentials><con:jmsConfig JMSDeliveryMode="PERSISTENT"/><con:jmsPropertyConfig/><con:parameters>
  <con:entry key="tokenType" value=""/>
  <con:entry key="token" value=""/>
</con:parameters><con:parameterOrder><con:entry>Authorization</con:entry><con:entry>tokenType</con:entry><con:entry>token</con:entry></con:parameterOrder></con:request></con:method></con:resource><con:resource name="signin" path="signin" id="4d553fbf-f353-4c88-bd64-baf40595902f"><con:settings/><con:parameters><con:parameter><con:name>account</con:name><con:value/><con:style>PLAIN</con:style><con:default/><con:description xsi:nil="true"/></con:parameter><con:parameter><con:name>username</con:name><con:value/><con:style>PLAIN</con:style><con:default/><con:description xsi:nil="true"/></con:parameter><con:parameter><con:name>password</con:name><con:value/><con:style>PLAIN</con:style><con:default/><con:description xsi:nil="true"/></con:parameter></con:parameters><con:method name="Method 1" id="9d442765-edf1-4e5a-90b7-fb5672d2d951" method="POST"><con:settings/><con:parameters/><con:representation type="REQUEST"><con:mediaType>application/json</con:mediaType><con:params/></con:representation><con:representation type="FAULT"><con:mediaType>application/json</con:mediaType><con:status>400</con:status><con:params/><con:element xmlns:sig="http://development.mawashi.tools/api/rest/v1.0/auth/signin">sig:Fault</con:element></con:representation><con:representation type="RESPONSE"><con:mediaType>application/json</con:mediaType><con:status>200</con:status><con:params/><con:element xmlns:sig="http://development.mawashi.tools/api/rest/v1.0/auth/signin">sig:Response</con:element></con:representation><con:request name="Request 1" id="190e287d-d047-4789-9b14-6b98fa65a3d3" mediaType="application/json" postQueryString="false"><con:settings><con:setting id="com.eviware.soapui.impl.wsdl.WsdlRequest@request-headers">&lt;xml-fragment/></con:setting></con:settings><con:endpoint>http://development.mawashi.tools:8080</con:endpoint><con:request>{
	"account":"alinka",
	"password":"alinana25",
	"username":"alinka25@aaa.aaa"
	}</con:request><con:originalUri>http://development.mawashi.tools/api/rest/v1.0/auth/signin</con:originalUri><con:credentials><con:authType>No Authorization</con:authType></con:credentials><con:jmsConfig JMSDeliveryMode="PERSISTENT"/><con:jmsPropertyConfig/><con:parameters>
  <con:entry key="tokenType" value=""/>
  <con:entry key="token" value=""/>
</con:parameters><con:parameterOrder><con:entry>Authorization</con:entry><con:entry>account</con:entry><con:entry>username</con:entry><con:entry>password</con:entry><con:entry>tokenType</con:entry><con:entry>token</con:entry></con:parameterOrder></con:request></con:method></con:resource></con:resource><con:method name="Method 1" id="befdcee9-6981-4c25-bf2f-2c4d71df92ee" method="GET"><con:settings/><con:parameters/><con:representation type="FAULT"><con:mediaType>application/json;charset=UTF-8</con:mediaType><con:status>401</con:status><con:params/><con:element xmlns:v1="http://development.mawashi.tools/api/rest/v1.0/">v1:Fault</con:element></con:representation><con:representation type="RESPONSE"><con:mediaType>application/json</con:mediaType><con:status>200</con:status><con:params/><con:element xmlns:v1="http://development.mawashi.tools/api/rest/v1.0/">v1:Response</con:element></con:representation><con:request name="Request 1" id="96a97d4e-df6d-4869-a87e-4a92b61b0cf5" mediaType="application/json"><con:settings><con:setting id="com.eviware.soapui.impl.wsdl.WsdlRequest@request-headers">&lt;xml-fragment/></con:setting></con:settings><con:endpoint>http://development.mawashi.tools:8080</con:endpoint><con:request/><con:originalUri>http://development.mawashi.tools/api/rest/v1.0/</con:originalUri><con:credentials><con:authType>No Authorization</con:authType></con:credentials><con:jmsConfig JMSDeliveryMode="PERSISTENT"/><con:jmsPropertyConfig/><con:parameters><entry key="Authorization" value="Bearer eyJhbGciOiJIUzUxMiJ9.eyJzdWIiOiI1NjkiLCJpYXQiOjE1OTk5MjQxMDksImV4cCI6MTYwMDUyODkwOX0.eQRmOOxQ9lXdcNXCfrJdvzhpuz3K5cRM8W0Nd7nup8Iu7hlMRunfwsFUU_wMZvduiwywCTLRBBvRzMw6s9X-NA" xmlns="http://eviware.com/soapui/config"/></con:parameters><con:parameterOrder><con:entry>Authorization</con:entry><con:entry>tokenType</con:entry><con:entry>token</con:entry></con:parameterOrder></con:request></con:method></con:resource></con:interface><con:testSuite id="f4c5e65d-305b-4327-b25b-a82e1c1da067" name="TestSuite 1"><con:settings/><con:runType>SEQUENTIAL</con:runType><con:testCase id="3f854a49-164f-4653-952f-01642bf26195" failOnError="true" failTestCaseOnErrors="true" keepSession="false" maxResults="0" name="SigninTest" searchProperties="true"><con:settings/><con:testStep type="properties" name="TestData" id="fa339a2f-2533-45d5-97c5-c0bb1b8032f6"><con:settings/><con:config xsi:type="con:PropertiesStep" saveFirst="true" xmlns:xsi="http://www.w3.org/2001/XMLSchema-instance"><con:properties><con:property><con:name>account</con:name><con:value>${=java.util.UUID.randomUUID()}</con:value></con:property><con:property><con:name>username</con:name><con:value>${=java.util.UUID.randomUUID()}@test.mail</con:value></con:property><con:property><con:name>password</con:name><con:value>sdffdsA1</con:value></con:property></con:properties></con:config></con:testStep><con:testStep type="restrequest" name="SignupTest" id="affab438-4531-4aff-b17f-0eced3de1ab1"><con:settings/><con:config service="http://development.mawashi.tools:8080" resourcePath="/api/rest/v1.0/auth/signup" methodName="Method 1" xsi:type="con:RestRequestStep" xmlns:xsi="http://www.w3.org/2001/XMLSchema-instance"><con:restRequest name="SignupTest" id="eed712fe-9537-417d-ae64-84d705681521" mediaType="application/json" postQueryString="false"><con:settings><con:setting id="com.eviware.soapui.impl.wsdl.WsdlRequest@request-headers">&lt;xml-fragment/></con:setting></con:settings><con:endpoint>http://development.mawashi.tools:8080</con:endpoint><con:request>{
	"account":"${TestData#account}",
	"password":"${TestData#password}",
	"username":"${TestData#username}"
	
	}</con:request><con:originalUri>http://development.mawashi.tools/api/rest/v1.0/auth/signup</con:originalUri><con:assertion type="Valid HTTP Status Codes" id="552605e3-b972-4769-a32d-caab8a047ead" name="Valid HTTP Status Codes"><con:configuration><codes>201</codes></con:configuration></con:assertion><con:assertion type="Simple Contains" id="7029acb4-5202-41f9-b0db-52aa07f357f5" name="Contains"><con:configuration><token>test.mail</token><ignoreCase>false</ignoreCase><useRegEx>false</useRegEx></con:configuration></con:assertion><con:assertion type="Invalid HTTP Status Codes" id="d6797754-7a83-4d1e-933f-10713121da30" name="Invalid HTTP Status Codes"><con:configuration><codes>401</codes></con:configuration></con:assertion><con:assertion type="JsonPath Match" id="20d1a2f6-915c-49a0-bd17-9ea46e2f53c1" name="JsonPath Match"><con:configuration><path>success</path><content>true</content><allowWildcards>false</allowWildcards><ignoreNamspaceDifferences>false</ignoreNamspaceDifferences><ignoreComments>false</ignoreComments></con:configuration></con:assertion><con:assertion type="JsonPath Match" id="919a7ffb-bdb3-4b18-b5d5-903caa63989c" name="JsonPath Match 1"><con:configuration><path>error</path><content>null</content><allowWildcards>false</allowWildcards><ignoreNamspaceDifferences>false</ignoreNamspaceDifferences><ignoreComments>false</ignoreComments></con:configuration></con:assertion><con:credentials><con:authType>No Authorization</con:authType></con:credentials><con:jmsConfig JMSDeliveryMode="PERSISTENT"/><con:jmsPropertyConfig/><con:parameters>
  <con:entry key="tokenType" value=""/>
  <con:entry key="token" value=""/>
</con:parameters><con:parameterOrder><con:entry>Authorization</con:entry><con:entry>tokenType</con:entry><con:entry>token</con:entry></con:parameterOrder></con:restRequest></con:config></con:testStep><con:testStep type="transfer" name="AccountTransfer" id="d2a91e60-1a8e-40dd-8a9e-25e9f1ae29ef"><con:settings/><con:config xsi:type="con:PropertyTransfersStep" xmlns:xsi="http://www.w3.org/2001/XMLSchema-instance"><con:transfers setNullOnMissingSource="true" transferTextContent="true" failOnError="true" ignoreEmpty="false" transferToAll="false" entitize="false" transferChildNodes="false"><con:name>accounttransfer</con:name><con:sourceType>Response</con:sourceType><con:sourceStep>SignupTest</con:sourceStep><con:sourcePath>data.account.name</con:sourcePath><con:targetType>account</con:targetType><con:targetStep>SigninTest</con:targetStep><con:type>JSONPATH</con:type><con:targetTransferType>JSONPATH</con:targetTransferType><con:upgraded>true</con:upgraded></con:transfers><con:transfers setNullOnMissingSource="true" transferTextContent="true" failOnError="true" ignoreEmpty="false" transferToAll="false" entitize="false" transferChildNodes="false"><con:name>usernamestransfer</con:name><con:sourceType>Response</con:sourceType><con:sourceStep>SignupTest</con:sourceStep><con:sourcePath>data.username</con:sourcePath><con:targetType>username</con:targetType><con:targetStep>SigninTest</con:targetStep><con:type>JSONPATH</con:type><con:targetTransferType>JSONPATH</con:targetTransferType><con:upgraded>true</con:upgraded></con:transfers><con:transfers setNullOnMissingSource="true" transferTextContent="true" failOnError="true" ignoreEmpty="false" transferToAll="false" entitize="false" transferChildNodes="false"><con:name>passwordtransfer</con:name><con:sourceType>password</con:sourceType><con:sourceStep>TestData</con:sourceStep><con:sourcePath/><con:targetType>password</con:targetType><con:targetStep>SigninTest</con:targetStep><con:type>XPATH</con:type><con:targetTransferType>XPATH</con:targetTransferType><con:upgraded>true</con:upgraded></con:transfers></con:config></con:testStep><con:testStep type="restrequest" name="SigninTest" id="0ba12b7c-b7fd-49b8-8068-adac9e2932d6"><con:settings/><con:config service="http://development.mawashi.tools:8080" resourcePath="/api/rest/v1.0/auth/signin" methodName="Method 1" xsi:type="con:RestRequestStep" xmlns:xsi="http://www.w3.org/2001/XMLSchema-instance"><con:restRequest name="SigninTest" id="190e287d-d047-4789-9b14-6b98fa65a3d3" mediaType="application/json" postQueryString="false"><con:settings><con:setting id="com.eviware.soapui.impl.wsdl.WsdlRequest@request-headers">&lt;xml-fragment/></con:setting></con:settings><con:endpoint>http://development.mawashi.tools:8080</con:endpoint><con:request>{
	"account":"${#account}",
	"password":"${#password}",
	"username":"${#username}"
	}</con:request><con:originalUri>http://development.mawashi.tools/api/rest/v1.0/auth/signin</con:originalUri><con:assertion type="Valid HTTP Status Codes" id="e541a8ca-2809-4284-a1d2-1d0ca70d1211" name="Valid HTTP Status Codes"><con:configuration><codes>200</codes></con:configuration></con:assertion><con:assertion type="Invalid HTTP Status Codes" id="db7eca53-a7af-466e-90c3-24ddcb8c95f2" name="Invalid HTTP Status Codes"><con:configuration><codes>400</codes></con:configuration></con:assertion><con:assertion type="Simple Contains" id="5312a1a3-4500-49a9-a591-da16ebee92e4" name="Contains"><con:configuration><token>Bearer</token><ignoreCase>false</ignoreCase><useRegEx>false</useRegEx></con:configuration></con:assertion><con:assertion type="JsonPath Match" id="eebe3cca-73e0-4cd0-b4b6-d3a061926d05" name="JsonPath Match"><con:configuration><path>success</path><content>true</content><allowWildcards>false</allowWildcards><ignoreNamspaceDifferences>false</ignoreNamspaceDifferences><ignoreComments>false</ignoreComments></con:configuration></con:assertion><con:assertion type="JsonPath Match" id="911acc60-a619-49bc-9d84-dced0aae8183" name="JsonPath Match 1"><con:configuration><path>error</path><content>null</content><allowWildcards>false</allowWildcards><ignoreNamspaceDifferences>false</ignoreNamspaceDifferences><ignoreComments>false</ignoreComments></con:configuration></con:assertion><con:credentials><con:authType>No Authorization</con:authType></con:credentials><con:jmsConfig JMSDeliveryMode="PERSISTENT"/><con:jmsPropertyConfig/><con:parameters>
  <con:entry key="password" value="sdffdsA1"/>
  <con:entry key="tokenType" value=""/>
  <con:entry key="account" value="cfd980d7-d424-4374-9c49-e626e20f0342"/>
  <con:entry key="username" value="08079974-2bb1-450a-8b51-dda3f30658f5@test.mail"/>
  <con:entry key="token" value=""/>
</con:parameters><con:parameterOrder><con:entry>Authorization</con:entry><con:entry>account</con:entry><con:entry>username</con:entry><con:entry>password</con:entry><con:entry>tokenType</con:entry><con:entry>token</con:entry></con:parameterOrder></con:restRequest></con:config></con:testStep><con:testStep type="transfer" name="TokenTransfer" id="66063b8b-d183-4423-982f-00c167285a49"><con:settings/><con:config xsi:type="con:PropertyTransfersStep" xmlns:xsi="http://www.w3.org/2001/XMLSchema-instance"><con:transfers setNullOnMissingSource="true" transferTextContent="true" failOnError="true" ignoreEmpty="false" transferToAll="false" entitize="false" transferChildNodes="false"><con:name>tokenTypeTransfer</con:name><con:sourceType>Response</con:sourceType><con:sourceStep>SigninTest</con:sourceStep><con:sourcePath>data.tokenType</con:sourcePath><con:targetType>tokenType</con:targetType><con:targetStep>GetAllRequests</con:targetStep><con:type>JSONPATH</con:type><con:targetTransferType>JSONPATH</con:targetTransferType><con:upgraded>true</con:upgraded></con:transfers><con:transfers setNullOnMissingSource="true" transferTextContent="true" failOnError="true" ignoreEmpty="false" transferToAll="false" entitize="false" transferChildNodes="false"><con:name>tokenTransfer</con:name><con:sourceType>Response</con:sourceType><con:sourceStep>SigninTest</con:sourceStep><con:sourcePath>data.accessToken</con:sourcePath><con:targetType>token</con:targetType><con:targetStep>GetAllRequests</con:targetStep><con:type>JSONPATH</con:type><con:targetTransferType>JSONPATH</con:targetTransferType><con:upgraded>true</con:upgraded></con:transfers></con:config></con:testStep><con:testStep type="restrequest" name="GetAllRequests" id="bd6d5342-f612-4a34-9914-ebaff864acb1"><con:settings/><con:config service="http://development.mawashi.tools:8080" resourcePath="/api/rest/v1.0" methodName="Method 1" xsi:type="con:RestRequestStep" xmlns:xsi="http://www.w3.org/2001/XMLSchema-instance"><con:restRequest name="GetAllRequests" id="96a97d4e-df6d-4869-a87e-4a92b61b0cf5" mediaType="application/json"><con:settings><con:setting id="com.eviware.soapui.impl.wsdl.WsdlRequest@request-headers">&lt;xml-fragment/></con:setting></con:settings><con:endpoint>http://development.mawashi.tools:8080</con:endpoint><con:request/><con:originalUri>http://development.mawashi.tools/api/rest/v1.0/</con:originalUri><con:assertion type="Valid HTTP Status Codes" id="7b1aa1ac-9b6f-4f7f-aa60-646087bcba46" name="Valid HTTP Status Codes"><con:configuration><codes>200</codes></con:configuration></con:assertion><con:assertion type="Invalid HTTP Status Codes" id="e81a8c4f-2cbd-489f-be5c-8093957506f2" name="Invalid HTTP Status Codes"><con:configuration><codes>400</codes></con:configuration></con:assertion><con:assertion type="Simple Contains" id="e6d58789-0ef7-4156-8b72-fe8ebf2cacf8" name="Contains"><con:configuration><token>signin
signup</token><ignoreCase>false</ignoreCase><useRegEx>false</useRegEx></con:configuration></con:assertion><con:assertion type="JsonPath Match" id="718f1296-58b6-4c8b-bcca-dca796374720" name="JsonPath Match"><con:configuration><path>success</path><content>true</content><allowWildcards>false</allowWildcards><ignoreNamspaceDifferences>false</ignoreNamspaceDifferences><ignoreComments>false</ignoreComments></con:configuration></con:assertion><con:assertion type="JsonPath Match" id="01a840e4-b2cf-40f8-a8a8-70c8ecb460ce" name="JsonPath Match 1"><con:configuration><path>error</path><content>null</content><allowWildcards>false</allowWildcards><ignoreNamspaceDifferences>false</ignoreNamspaceDifferences><ignoreComments>false</ignoreComments></con:configuration></con:assertion><con:credentials><con:authType>No Authorization</con:authType></con:credentials><con:jmsConfig JMSDeliveryMode="PERSISTENT"/><con:jmsPropertyConfig/><con:parameters>
  <con:entry key="Authorization" value="${#tokenType} ${#token}"/>
  <con:entry key="tokenType" value="Bearer"/>
  <con:entry key="token" value="eyJhbGciOiJIUzUxMiJ9.eyJzdWIiOiI1NzYiLCJpYXQiOjE1OTk5MjcyNzgsImV4cCI6MTYwMDUzMjA3OH0.oc5BePteybuiVLZMu2DP2UyLnBEe7jMuOkBTuxFCzs8NBODRHRSR-Dgey7QC1JtowblmSq70ZkWCneCYbM1zJQ"/>
</con:parameters><con:parameterOrder><con:entry>Authorization</con:entry><con:entry>tokenType</con:entry><con:entry>token</con:entry></con:parameterOrder></con:restRequest></con:config></con:testStep><con:properties/></con:testCase><con:properties/></con:testSuite><con:properties/><con:wssContainer/><con:oAuth2ProfileContainer/><con:oAuth1ProfileContainer/></con:soapui-project>